pcloud/__init__.py
pcloud/api.py
pcloud/binaryprotocol.py
pcloud/dummyprotocol.py
pcloud/jsonprotocol.py
pcloud/oauth2.py
pcloud/protocols.py
pcloud/utils.py
pcloud/validate.py
pcloud/tests/conftest.py
pcloud/tests/server.py
pcloud/tests/test_api.py
pcloud/tests/test_helpers.py
pcloud/tests/test_integration.py
pcloud/tests/test_oauth2.py
pcloud/tests/test_validate.py
pcloud/tests/data/extractarchive.json
pcloud/tests/data/getdigest.json
pcloud/tests/data/upload.txt
pcloud/tests/data/userinfo.json
pcloud-2.0.1.dist-info/licenses/LICENSE
pcloud-2.0.1.dist-info/METADATA
pcloud-2.0.1.dist-info/WHEEL
pcloud-2.0.1.dist-info/top_level.txt
pcloud-2.0.1.dist-info/RECORD
