Metadata-Version: 2.4
Name: pcloud
Version: 2.0.1
Summary: A client library for pCloud
Author-email: Tom Gross <itconsense@gmail.com>
License-Expression: MIT
Keywords: Python,pCloud,REST
Classifier: Development Status :: 5 - Production/Stable
Classifier: Intended Audience :: Developers
Classifier: Environment :: Console
Classifier: Environment :: Other Environment
Classifier: Environment :: Web Environment
Classifier: Programming Language :: Python
Classifier: Programming Language :: Python :: 3.10
Classifier: Programming Language :: Python :: 3.11
Classifier: Programming Language :: Python :: 3.12
Classifier: Programming Language :: Python :: 3.13
Classifier: Programming Language :: Python :: 3.14
Classifier: Operating System :: OS Independent
Classifier: Topic :: Software Development :: Libraries :: Python Modules
License-File: LICENSE
Requires-Dist: httpx>=0.28.1
Requires-Dist: setuptools>=80.9.0
Requires-Dist: wheel>=0.45.1
Provides-Extra: test
Requires-Dist: pytest==8.4.2; extra == "test"
Requires-Dist: pytest-sugar==1.1.1; extra == "test"
Requires-Dist: wheel==0.45.1; extra == "test"
Requires-Dist: flake8==7.3.0; extra == "test"
Requires-Dist: playwright==1.55.0; extra == "test"
Requires-Dist: multipart==1.3.0; extra == "test"
Requires-Dist: zipp>=3.23.0; extra == "test"
Dynamic: license-file
